{"Thu May 04 19:53:32 +0000 2017": [{"user": 40676546, "text": "#Hellohi #Hellohiworldtour #mykewithay #buffalo Today's adventure is the @buffalostate 50th... https://t.co/7CjqPh9eZj", "datetime": "Thu May 04 19:53:32 +0000 2017", "latitude": 42.93361581, "longitude": -78.87762828}], "Sat May 02 14:32:30 +0000 2015": [{"user": 553034790, "text": "Need something to do today who wants to adventure", "datetime": "Sat May 02 14:32:30 +0000 2015", "latitude": 42.93639027, "longitude": -78.88402773}], "Sat Sep 09 19:24:21 +0000 2017": [{"user": 69796241, "text": "The things you find at the local grocery store when traveling @ Wegmans https://t.co/kg9kodfqBp", "datetime": "Sat Sep 09 19:24:21 +0000 2017", "latitude": 42.939209, "longitude": -78.8827209}]}