{"2351613497": [{"id": 780980019573030913, "datetime": "Wed Sep 28 03:58:41 +0000 2016", "text": "It kinda looks creepy #nofilter #nature #walks #creepy @ Fort Erie, Ontario https://t.co/trtaKsWEJR", "user_id": 2351613497, "user_location_str": "Ontario, Canada ", "location": {"type": "Point", "coordinates": [42.9, -78.9333]}, "hashtags": [{"text": "nofilter", "indices": [22, 31]}, {"text": "nature", "indices": [32, 39]}, {"text": "walks", "indices": [40, 46]}, {"text": "creepy", "indices": [47, 54]}], "sentiment_text": "it kinda looks creepy @ fort erie, ontario", "parse": [{"it": {"pos_tag": "PRP", "lemma": "it", "ner": "O"}, "kinda": {"pos_tag": "VBD", "lemma": "kinda", "ner": "O", "nsubj": "it", "ccomp": "looks"}, "looks": {"pos_tag": "VBZ", "lemma": "look", "ner": "O", "dobj": "creepy", "dep": "ontario"}, "creepy": {"pos_tag": "JJ", "lemma": "creepy", "ner": "O"}, "@": {"pos_tag": "SYM", "lemma": "@", "ner": "O"}, "fort": {"pos_tag": "NNP", "lemma": "fort", "ner": "CITY", "dep": "@"}, "erie": {"pos_tag": "NNP", "lemma": "erie", "ner": "CITY"}, ",": {"pos_tag": ",", "lemma": ",", "ner": "O"}, "ontario": {"pos_tag": "NNP", "lemma": "ontario", "ner": "STATE_OR_PROVINCE", "compound": "erie", "punct": ","}}], "emoticons": [], "opinionate": [true]}, {"id": 780979689816887296, "datetime": "Wed Sep 28 03:57:22 +0000 2016", "text": "I love going on nature walks #nofilter #nature #walks @ Fort Erie, Ontario https://t.co/B4Z1sVvQii", "user_id": 2351613497, "user_location_str": "Ontario, Canada ", "location": {"type": "Point", "coordinates": [42.9, -78.9333]}, "hashtags": [{"text": "nofilter", "indices": [29, 38]}, {"text": "nature", "indices": [39, 46]}, {"text": "walks", "indices": [47, 53]}], "sentiment_text": "i love going on nature walks @ fort erie, ontario", "parse": [{"i": {"pos_tag": "PRP", "lemma": "i", "ner": "O"}, "love": {"pos_tag": "VBP", "lemma": "love", "ner": "O", "nsubj": "i", "xcomp": "going"}, "going": {"pos_tag": "VBG", "lemma": "go", "ner": "O", "nmod": "nature"}, "on": {"pos_tag": "IN", "lemma": "on", "ner": "O"}, "nature": {"pos_tag": "NN", "lemma": "nature", "ner": "O", "case": "on", "acl:relcl": "walks", "punct": ",", "appos": "ontario"}, "walks": {"pos_tag": "VBZ", "lemma": "walk", "ner": "O", "ccomp": "erie"}, "@": {"pos_tag": "SYM", "lemma": "@", "ner": "O"}, "fort": {"pos_tag": "NNP", "lemma": "fort", "ner": "CITY"}, "erie": {"pos_tag": "NNP", "lemma": "erie", "ner": "CITY", "dep": "@", "compound": "fort"}, ",": {"pos_tag": ",", "lemma": ",", "ner": "O"}, "ontario": {"pos_tag": "NNP", "lemma": "ontario", "ner": "STATE_OR_PROVINCE"}}], "emoticons": [], "opinionate": [true]}, {"id": 916777184978718721, "datetime": "Sat Oct 07 21:28:08 +0000 2017", "text": "Nature is our friend so we must treat it right #greens #nature #mothernature #glasses #selfie... https://t.co/CITWPTngRK", "user_id": 2351613497, "user_location_str": "Ontario, Canada ", "location": {"type": "Point", "coordinates": [42.9, -78.9333]}, "hashtags": [{"text": "greens", "indices": [47, 54]}, {"text": "nature", "indices": [55, 62]}, {"text": "mothernature", "indices": [63, 76]}, {"text": "glasses", "indices": [77, 85]}, {"text": "selfie", "indices": [86, 93]}], "sentiment_text": "nature is our friend so we must treat it right .", "parse": [{"nature": {"pos_tag": "NNP", "lemma": "nature", "ner": "O"}, "is": {"pos_tag": "VBZ", "lemma": "be", "ner": "O"}, "our": {"pos_tag": "PRP$", "lemma": "we", "ner": "O"}, "friend": {"pos_tag": "NN", "lemma": "friend", "ner": "O", "nsubj": "nature", "cop": "is", "nmod:poss": "our", "advcl": "treat", "punct": "."}, "so": {"pos_tag": "IN", "lemma": "so", "ner": "O"}, "we": {"pos_tag": "PRP", "lemma": "we", "ner": "O"}, "must": {"pos_tag": "MD", "lemma": "must", "ner": "O"}, "treat": {"pos_tag": "VB", "lemma": "treat", "ner": "O", "mark": "so", "nsubj": "we", "aux": "must", "xcomp": "right"}, "it": {"pos_tag": "PRP", "lemma": "it", "ner": "O"}, "right": {"pos_tag": "RB", "lemma": "right", "ner": "O", "nsubj": "it"}, ".": {"pos_tag": ".", "lemma": ".", "ner": "O"}}], "emoticons": [], "opinionate": [true]}]}