{"119713144": [{"id": 654690830305783808, "datetime": "Thu Oct 15 16:10:32 +0000 2015", "text": "My badass unicorn wrist tattoo that I got while on vacation. @ Great Wolf Lodge        Niagara Falls, ON https://t.co/IGVtM1KQjX", "user_id": 119713144, "user_location_str": "Seattle, WA", "location": {"type": "Point", "coordinates": [43.11611264, -79.07118068]}, "hashtags": [], "sentiment_text": "my badass unicorn wrist tattoo that i got while on vacation. @ great wolf lodge niagara falls, on", "parse": [{"my": {"pos_tag": "PRP$", "lemma": "my", "ner": "O"}, "badass": {"pos_tag": "JJ", "lemma": "badass", "ner": "O"}, "unicorn": {"pos_tag": "NN", "lemma": "unicorn", "ner": "O"}, "wrist": {"pos_tag": "NN", "lemma": "wrist", "ner": "O"}, "tattoo": {"pos_tag": "NN", "lemma": "tattoo", "ner": "O", "nmod:poss": "my", "amod": "badass", "compound": "wrist", "dep": "got", "punct": "."}, "that": {"pos_tag": "IN", "lemma": "that", "ner": "O"}, "i": {"pos_tag": "PRP", "lemma": "i", "ner": "O"}, "got": {"pos_tag": "VBD", "lemma": "get", "ner": "O", "mark": "that", "nsubj": "i", "nmod": "vacation"}, "while": {"pos_tag": "IN", "lemma": "while", "ner": "O"}, "on": {"pos_tag": "IN", "lemma": "on", "ner": "O"}, "vacation": {"pos_tag": "NN", "lemma": "vacation", "ner": "O", "case": "on"}, ".": {"pos_tag": ".", "lemma": ".", "ner": "O"}}, {"@": {"pos_tag": "SYM", "lemma": "@", "ner": "O"}, "great": {"pos_tag": "NNP", "lemma": "great", "ner": "LOCATION"}, "wolf": {"pos_tag": "NNP", "lemma": "wolf", "ner": "LOCATION"}, "lodge": {"pos_tag": "NNP", "lemma": "lodge", "ner": "LOCATION"}, "niagara": {"pos_tag": "NNP", "lemma": "niagara", "ner": "CITY"}, "falls": {"pos_tag": "NNP", "lemma": "falls", "ner": "CITY", "dep": "@", "compound": "niagara", "punct": ",", "acl": "on"}, ",": {"pos_tag": ",", "lemma": ",", "ner": "O"}, "on": {"pos_tag": "IN", "lemma": "on", "ner": "O"}}], "emoticons": [], "opinionate": [true, true]}, {"id": 654024166434308098, "datetime": "Tue Oct 13 20:01:27 +0000 2015", "text": "Wolf ears, wolf stuffie, MagiQuest wand...all set for my totally grown-up vacation. @ Great Wolf... https://t.co/hJ30RVBDjE", "user_id": 119713144, "user_location_str": "Seattle, WA", "location": {"type": "Point", "coordinates": [43.11611264, -79.07118068]}, "hashtags": [], "sentiment_text": "wolf ears, wolf stuffie, magiquest wand.all set for my totally grown-up vacation. @ great wolf.", "parse": [{"wolf": {"pos_tag": "NN", "lemma": "wolf", "ner": "O"}, "ears": {"pos_tag": "NNS", "lemma": "ear", "ner": "O", "compound": "wolf", "punct": ".", "appos": "set"}, ",": {"pos_tag": ",", "lemma": ",", "ner": "O"}, "stuffie": {"pos_tag": "NN", "lemma": "stuffie", "ner": "O", "compound": "wolf"}, "magiquest": {"pos_tag": "JJS", "lemma": "magiquest", "ner": "O"}, "wand.all": {"pos_tag": "JJ", "lemma": "wand.all", "ner": "O"}, "set": {"pos_tag": "NN", "lemma": "set", "ner": "O", "amod": "wand.all", "nmod": "vacation"}, "for": {"pos_tag": "IN", "lemma": "for", "ner": "O"}, "my": {"pos_tag": "PRP$", "lemma": "my", "ner": "O"}, "totally": {"pos_tag": "RB", "lemma": "totally", "ner": "O"}, "grown-up": {"pos_tag": "JJ", "lemma": "grown-up", "ner": "O", "advmod": "totally"}, "vacation": {"pos_tag": "NN", "lemma": "vacation", "ner": "O", "case": "for", "nmod:poss": "my", "amod": "grown-up"}, ".": {"pos_tag": ".", "lemma": ".", "ner": "O"}}, {"@": {"pos_tag": "SYM", "lemma": "@", "ner": "O"}, "great": {"pos_tag": "NNP", "lemma": "great", "ner": "PERSON", "dep": "wolf"}, "wolf": {"pos_tag": "NNP", "lemma": "wolf", "ner": "PERSON", "punct": "."}, ".": {"pos_tag": ".", "lemma": ".", "ner": "O"}}], "emoticons": [], "opinionate": [true, false]}], "257409019": [{"id": 919223878987030528, "datetime": "Sat Oct 14 15:30:25 +0000 2017", "text": "Go green #niagara #niagarafalls #ontario #canada #intothewild #naturalbeauty #travel #traveler... https://t.co/EurWY2uOg7", "user_id": 257409019, "user_location_str": "Bordeaux, France\n", "location": {"type": "Point", "coordinates": [43.1208, -79.0705]}, "hashtags": [{"text": "niagara", "indices": [9, 17]}, {"text": "niagarafalls", "indices": [18, 31]}, {"text": "ontario", "indices": [32, 40]}, {"text": "canada", "indices": [41, 48]}, {"text": "intothewild", "indices": [49, 61]}, {"text": "naturalbeauty", "indices": [62, 76]}, {"text": "travel", "indices": [77, 84]}, {"text": "traveler", "indices": [85, 94]}], "sentiment_text": "go green .", "parse": [{"go": {"pos_tag": "VB", "lemma": "go", "ner": "O", "xcomp": "green", "punct": "."}, "green": {"pos_tag": "JJ", "lemma": "green", "ner": "O"}, ".": {"pos_tag": ".", "lemma": ".", "ner": "O"}}], "emoticons": [], "opinionate": [true]}], "145091070": [{"id": 640248933705469952, "datetime": "Sat Sep 05 19:43:35 +0000 2015", "text": "My mini vacation pics. #familytime #fam #lafamilia #timeout #vacation #greatwolflodge #chill... https://t.co/ajy6WyWAF4", "user_id": 145091070, "user_location_str": "Toronto, Canada", "location": {"type": "Point", "coordinates": [43.11611167, -79.07118076]}, "hashtags": [{"text": "familytime", "indices": [23, 34]}, {"text": "fam", "indices": [35, 39]}, {"text": "lafamilia", "indices": [40, 50]}, {"text": "timeout", "indices": [51, 59]}, {"text": "vacation", "indices": [60, 69]}, {"text": "greatwolflodge", "indices": [70, 85]}, {"text": "chill", "indices": [86, 92]}], "sentiment_text": "my mini vacation pics. .", "parse": [{"my": {"pos_tag": "PRP$", "lemma": "my", "ner": "O"}, "mini": {"pos_tag": "JJ", "lemma": "mini", "ner": "O"}, "vacation": {"pos_tag": "NN", "lemma": "vacation", "ner": "O", "nmod:poss": "my", "amod": "mini", "dep": "pics", "punct": "."}, "pics": {"pos_tag": "NNS", "lemma": "pic", "ner": "O"}, ".": {"pos_tag": ".", "lemma": ".", "ner": "O"}}, {".": {"pos_tag": ".", "lemma": ".", "ner": "O"}}], "emoticons": [], "opinionate": [false, false]}], "23928626": [{"id": 629660388297154560, "datetime": "Fri Aug 07 14:28:29 +0000 2015", "text": "Niagara Whirlphool #NiagaraFalls #Nature @ Niagara Falls, ON Whirlpool https://t.co/I8OR8ktYl2", "user_id": 23928626, "user_location_str": "Wall Street, USA", "location": {"type": "Point", "coordinates": [43.12321221, -79.06849224]}, "hashtags": [{"text": "NiagaraFalls", "indices": [19, 32]}, {"text": "Nature", "indices": [33, 40]}], "sentiment_text": "niagara whirlphool @ niagara falls, on whirlpool", "parse": [{"niagara": {"pos_tag": "NNP", "lemma": "niagara", "ner": "CITY", "dep": "@"}, "whirlphool": {"pos_tag": "NNP", "lemma": "whirlphool", "ner": "O", "compound": "niagara", "acl:relcl": "niagara", "dep": "falls"}, "@": {"pos_tag": "SYM", "lemma": "@", "ner": "O"}, "falls": {"pos_tag": "NNP", "lemma": "falls", "ner": "CITY", "punct": ",", "appos": "whirlpool"}, ",": {"pos_tag": ",", "lemma": ",", "ner": "O"}, "on": {"pos_tag": "NNP", "lemma": "on", "ner": "STATE_OR_PROVINCE"}, "whirlpool": {"pos_tag": "NNP", "lemma": "whirlpool", "ner": "ORGANIZATION", "compound": "on"}}], "emoticons": [], "opinionate": [true]}], "123421220": [{"id": 889269177667735552, "datetime": "Sun Jul 23 23:41:08 +0000 2017", "text": "One super cool #niagarafalls attraction I would never heard of, but super fun! #travel #aerocar #... https://t.co/jaPP6tCk9z", "user_id": 123421220, "user_location_str": "Toronto, Ontario", "location": {"type": "Point", "coordinates": [43.118, -79.0688]}, "hashtags": [{"text": "niagarafalls", "indices": [15, 28]}, {"text": "travel", "indices": [75, 82]}, {"text": "aerocar", "indices": [83, 91]}], "sentiment_text": "one super cool attraction i would never heard of, but super fun! #.", "parse": [{"one": {"pos_tag": "CD", "lemma": "one", "ner": "NUMBER", "dep": "heard", "punct": "!", "nmod": "fun"}, "super": {"pos_tag": "JJ", "lemma": "super", "ner": "O"}, "cool": {"pos_tag": "JJ", "lemma": "cool", "ner": "O"}, "attraction": {"pos_tag": "NN", "lemma": "attraction", "ner": "O", "amod": "cool"}, "i": {"pos_tag": "PRP", "lemma": "i", "ner": "O"}, "would": {"pos_tag": "MD", "lemma": "would", "ner": "O"}, "never": {"pos_tag": "RB", "lemma": "never", "ner": "O"}, "heard": {"pos_tag": "VBN", "lemma": "hear", "ner": "O", "nsubj": "i", "aux": "would", "neg": "never", "nmod": "of"}, "of": {"pos_tag": "IN", "lemma": "of", "ner": "O"}, ",": {"pos_tag": ",", "lemma": ",", "ner": "O"}, "but": {"pos_tag": "CC", "lemma": "but", "ner": "O"}, "fun": {"pos_tag": "NN", "lemma": "fun", "ner": "O", "case": "but", "amod": "super"}, "!": {"pos_tag": ".", "lemma": "!", "ner": "O"}}, {"#": {"pos_tag": "#", "lemma": "#", "ner": "O", "punct": "."}, ".": {"pos_tag": ".", "lemma": ".", "ner": "O"}}], "emoticons": [], "opinionate": [true, false]}], "258398938": [{"id": 987738974562091008, "datetime": "Sat Apr 21 17:04:57 +0000 2018", "text": "[?]/[?]......#niagarafalls #niagara #canada #ontario #cablecar #rapids #nature... https://t.co/M6BaS5M2hA", "user_id": 258398938, "user_location_str": "Here and there", "location": {"type": "Point", "coordinates": [43.1208, -79.0699]}, "hashtags": [{"text": "niagarafalls", "indices": [21, 34]}, {"text": "niagara", "indices": [35, 43]}, {"text": "canada", "indices": [44, 51]}, {"text": "ontario", "indices": [52, 60]}, {"text": "cablecar", "indices": [61, 70]}, {"text": "rapids", "indices": [71, 78]}, {"text": "nature", "indices": [79, 86]}], "sentiment_text": "[?]/[?].", "parse": [{"-lsb-": {"pos_tag": "-LRB-", "lemma": "-lsb-", "ner": "O", "punct": "-rsb-"}, "?": {"pos_tag": ".", "lemma": "?", "ner": "O"}, "-rsb-": {"pos_tag": "-RRB-", "lemma": "-rsb-", "ner": "O"}}, {"/": {"pos_tag": ":", "lemma": "/", "ner": "O"}, "-lsb-": {"pos_tag": "-LRB-", "lemma": "-lsb-", "ner": "O", "punct": "-rsb-"}, "?": {"pos_tag": ".", "lemma": "?", "ner": "O"}, "-rsb-": {"pos_tag": "-RRB-", "lemma": "-rsb-", "ner": "O"}}, {".": {"pos_tag": ".", "lemma": ".", "ner": "O"}}], "emoticons": [], "opinionate": [false, false, false]}], "85374554": [{"id": 721724851212263425, "datetime": "Sun Apr 17 15:39:48 +0000 2016", "text": "Nature is beautiful. #niagaragorge @ Niagara Gorge https://t.co/0tUGci3b2c", "user_id": 85374554, "user_location_str": "Saugerties, NY", "location": {"type": "Point", "coordinates": [43.1208, -79.0705]}, "hashtags": [{"text": "niagaragorge", "indices": [21, 34]}], "sentiment_text": "nature is beautiful. @ niagara gorge", "parse": [{"nature": {"pos_tag": "NNP", "lemma": "nature", "ner": "O"}, "is": {"pos_tag": "VBZ", "lemma": "be", "ner": "O"}, "beautiful": {"pos_tag": "JJ", "lemma": "beautiful", "ner": "O", "nsubj": "nature", "cop": "is", "punct": "."}, ".": {"pos_tag": ".", "lemma": ".", "ner": "O"}}, {"@": {"pos_tag": "SYM", "lemma": "@", "ner": "O"}, "niagara": {"pos_tag": "NNP", "lemma": "niagara", "ner": "LOCATION"}, "gorge": {"pos_tag": "NNP", "lemma": "gorge", "ner": "LOCATION", "dep": "@", "compound": "niagara"}}], "emoticons": [], "opinionate": [true, false]}], "9409982": [{"id": 715656360864534529, "datetime": "Thu Mar 31 21:45:47 +0000 2016", "text": "Linen stitch scarves make for excellent #vacation #knitting. #malabrigo @ Great Wolf Lodge https://t.co/BPOdsvyMPt", "user_id": 9409982, "user_location_str": "Toronto", "location": {"type": "Point", "coordinates": [43.1159964, -79.07130124]}, "hashtags": [{"text": "vacation", "indices": [40, 49]}, {"text": "knitting", "indices": [50, 59]}, {"text": "malabrigo", "indices": [61, 71]}], "sentiment_text": "linen stitch scarves make for excellent @ great wolf lodge", "parse": [{"linen": {"pos_tag": "NN", "lemma": "linen", "ner": "O"}, "stitch": {"pos_tag": "NN", "lemma": "stitch", "ner": "O"}, "scarves": {"pos_tag": "NNS", "lemma": "scarf", "ner": "O", "compound": "stitch"}, "make": {"pos_tag": "VBP", "lemma": "make", "ner": "O", "nsubj": "scarves", "nmod": "excellent"}, "for": {"pos_tag": "IN", "lemma": "for", "ner": "O"}, "excellent": {"pos_tag": "JJ", "lemma": "excellent", "ner": "O", "case": "for", "dep": "great"}, "@": {"pos_tag": "SYM", "lemma": "@", "ner": "O"}, "great": {"pos_tag": "NNP", "lemma": "great", "ner": "LOCATION", "dep": "lodge"}, "wolf": {"pos_tag": "NNP", "lemma": "wolf", "ner": "LOCATION"}, "lodge": {"pos_tag": "NNP", "lemma": "lodge", "ner": "LOCATION", "compound": "wolf"}}], "emoticons": [], "opinionate": [true]}, {"id": 621464159927054336, "datetime": "Wed Jul 15 23:39:36 +0000 2015", "text": "Cast on for a new pair of socks because I am on vacation! #knitting @ Great Wolf Lodge        Niagara... https://t.co/nay2k3HaqR", "user_id": 9409982, "user_location_str": "Toronto", "location": {"type": "Point", "coordinates": [43.11611047, -79.07118243]}, "hashtags": [{"text": "knitting", "indices": [57, 66]}], "sentiment_text": "cast on for a new pair of socks because i am on vacation! @ great wolf lodge niagara.", "parse": [{"cast": {"pos_tag": "VBN", "lemma": "cast", "ner": "O", "nmod": "pair", "advcl": "vacation", "punct": "!"}, "on": {"pos_tag": "IN", "lemma": "on", "ner": "O"}, "for": {"pos_tag": "IN", "lemma": "for", "ner": "O"}, "a": {"pos_tag": "DT", "lemma": "a", "ner": "O"}, "new": {"pos_tag": "JJ", "lemma": "new", "ner": "O"}, "pair": {"pos_tag": "NN", "lemma": "pair", "ner": "O", "case": "for", "det": "a", "amod": "new", "nmod": "socks"}, "of": {"pos_tag": "IN", "lemma": "of", "ner": "O"}, "socks": {"pos_tag": "NNS", "lemma": "sock", "ner": "O", "case": "of"}, "because": {"pos_tag": "IN", "lemma": "because", "ner": "O"}, "i": {"pos_tag": "PRP", "lemma": "i", "ner": "O"}, "am": {"pos_tag": "VBP", "lemma": "be", "ner": "O"}, "vacation": {"pos_tag": "NN", "lemma": "vacation", "ner": "O", "mark": "because", "nsubj": "i", "cop": "am", "case": "on"}, "!": {"pos_tag": ".", "lemma": "!", "ner": "O"}}, {"@": {"pos_tag": "SYM", "lemma": "@", "ner": "O"}, "great": {"pos_tag": "NNP", "lemma": "great", "ner": "LOCATION"}, "wolf": {"pos_tag": "NNP", "lemma": "wolf", "ner": "LOCATION"}, "lodge": {"pos_tag": "NNP", "lemma": "lodge", "ner": "LOCATION", "dep": "niagara", "compound": "wolf"}, "niagara": {"pos_tag": "NNP", "lemma": "niagara", "ner": "LOCATION", "punct": "."}, ".": {"pos_tag": ".", "lemma": ".", "ner": "O"}}], "emoticons": [], "opinionate": [true, false]}], "814166202": [{"id": 676784248976744448, "datetime": "Tue Dec 15 15:21:53 +0000 2015", "text": "Our home today at @greatwolflodge vacation at #greatwolflodge @ Great... https://t.co/WmWrRslzXw", "user_id": 814166202, "user_location_str": "London, Ontario", "location": {"type": "Point", "coordinates": [43.11611264, -79.07118068]}, "hashtags": [{"text": "greatwolflodge", "indices": [46, 61]}], "sentiment_text": "our home today at vacation at @ great.", "parse": [{"our": {"pos_tag": "PRP$", "lemma": "we", "ner": "O"}, "home": {"pos_tag": "NN", "lemma": "home", "ner": "O"}, "today": {"pos_tag": "NN", "lemma": "today", "ner": "O", "nmod:poss": "our", "compound": "home", "nmod": "vacation", "acl": "great", "punct": "."}, "at": {"pos_tag": "IN", "lemma": "at", "ner": "O"}, "vacation": {"pos_tag": "NN", "lemma": "vacation", "ner": "O", "case": "at"}, "@": {"pos_tag": "SYM", "lemma": "@", "ner": "O"}, "great": {"pos_tag": "NNP", "lemma": "great", "ner": "O", "case": "at", "dep": "@"}, ".": {"pos_tag": ".", "lemma": ".", "ner": "O"}}], "emoticons": [], "opinionate": [true]}], "25294999": [{"id": 1050919465121181696, "datetime": "Sat Oct 13 01:21:40 +0000 2018", "text": "Mini #vacation (@ Great Wolf Niagara - @greatwolflodge in Niagara Falls, ON) https://t.co/nd4Rp8ie5T", "user_id": 25294999, "user_location_str": "Toronto, ON", "location": {"type": "Point", "coordinates": [43.11652, -79.07136]}, "hashtags": [{"text": "vacation", "indices": [5, 14]}], "sentiment_text": "mini (@ great wolf niagara - in niagara falls, on)", "parse": [{"mini": {"pos_tag": "NNP", "lemma": "mini", "ner": "O", "dep": "niagara"}, "-lrb-": {"pos_tag": "-LRB-", "lemma": "-lrb-", "ner": "O"}, "@": {"pos_tag": "SYM", "lemma": "@", "ner": "O"}, "great": {"pos_tag": "NNP", "lemma": "great", "ner": "LOCATION"}, "wolf": {"pos_tag": "NNP", "lemma": "wolf", "ner": "LOCATION"}, "niagara": {"pos_tag": "NNP", "lemma": "niagara", "ner": "CITY", "punct": "-rrb-", "dep": "@", "compound": "wolf", "parataxis": "on"}, "-": {"pos_tag": ":", "lemma": "-", "ner": "O"}, "in": {"pos_tag": "IN", "lemma": "in", "ner": "O"}, "falls": {"pos_tag": "NNP", "lemma": "falls", "ner": "CITY", "case": "in", "compound": "niagara", "punct": ","}, ",": {"pos_tag": ",", "lemma": ",", "ner": "O"}, "on": {"pos_tag": "NNP", "lemma": "on", "ner": "STATE_OR_PROVINCE", "nmod": "falls"}, "-rrb-": {"pos_tag": "-RRB-", "lemma": "-rrb-", "ner": "O"}}], "emoticons": [], "opinionate": [true]}], "960517753": [{"id": 845724047224815616, "datetime": "Sat Mar 25 19:48:20 +0000 2017", "text": "Even butterflies have to eat! #niagarafalls #ontheroad #travellingwithmom #travel #canada... https://t.co/2WOaa6fwGe", "user_id": 960517753, "user_location_str": "", "location": {"type": "Point", "coordinates": [43.11506, -79.06472]}, "hashtags": [{"text": "niagarafalls", "indices": [30, 43]}, {"text": "ontheroad", "indices": [44, 54]}, {"text": "travellingwithmom", "indices": [55, 73]}, {"text": "travel", "indices": [74, 81]}, {"text": "canada", "indices": [82, 89]}], "sentiment_text": "even butterflies have to eat! .", "parse": [{"even": {"pos_tag": "RB", "lemma": "even", "ner": "O"}, "butterflies": {"pos_tag": "NNS", "lemma": "butterfly", "ner": "O", "advmod": "even"}, "have": {"pos_tag": "VBP", "lemma": "have", "ner": "O", "nsubj": "butterflies", "xcomp": "eat", "punct": "!"}, "to": {"pos_tag": "TO", "lemma": "to", "ner": "O"}, "eat": {"pos_tag": "VB", "lemma": "eat", "ner": "O", "mark": "to"}, "!": {"pos_tag": ".", "lemma": "!", "ner": "O"}}, {".": {"pos_tag": ".", "lemma": ".", "ner": "O"}}], "emoticons": [], "opinionate": [true, false]}], "4644846312": [{"id": 726642762825654272, "datetime": "Sun May 01 05:21:49 +0000 2016", "text": "The hike back up - 130 steps up :D no prob ;). #hiking #niagarafalls #travel #roadtrip... https://t.co/Q56S08uvxN", "user_id": 4644846312, "user_location_str": "", "location": {"type": "Point", "coordinates": [43.11800432, -79.06875138]}, "hashtags": [{"text": "hiking", "indices": [47, 54]}, {"text": "niagarafalls", "indices": [55, 68]}, {"text": "travel", "indices": [69, 76]}, {"text": "roadtrip", "indices": [77, 86]}], "sentiment_text": "the hike back up - steps up :d no prob ;). .", "parse": [{"the": {"pos_tag": "DT", "lemma": "the", "ner": "O"}, "hike": {"pos_tag": "NN", "lemma": "hike", "ner": "O", "det": "the", "advmod": "up", "punct": ".", "dep": "steps"}, "back": {"pos_tag": "RB", "lemma": "back", "ner": "O"}, "up": {"pos_tag": "IN", "lemma": "up", "ner": "O", "advmod": "back"}, "-": {"pos_tag": ":", "lemma": "-", "ner": "O"}, "steps": {"pos_tag": "NNS", "lemma": "step", "ner": "O", "nmod": ":d", "dep": ";-rrb-"}, ":d": {"pos_tag": "NN", "lemma": ":d", "ner": "O", "case": "up"}, "no": {"pos_tag": "DT", "lemma": "no", "ner": "O"}, "prob": {"pos_tag": "NN", "lemma": "prob", "ner": "O"}, ";-rrb-": {"pos_tag": "NN", "lemma": ";-rrb-", "ner": "O", "neg": "no", "compound": "prob"}, ".": {"pos_tag": ".", "lemma": ".", "ner": "O"}}, {".": {"pos_tag": ".", "lemma": ".", "ner": "O"}}], "emoticons": [], "opinionate": [false, false]}], "3232217061": [{"id": 765716541811879936, "datetime": "Wed Aug 17 01:07:04 +0000 2016", "text": "She knows it is not something to run from now. do not run, do not.#destination #travel #traveler... https://t.co/fiQrmbIyki", "user_id": 3232217061, "user_location_str": "Central/South America", "location": {"type": "Point", "coordinates": [43.1208, -79.0705]}, "hashtags": [{"text": "destination", "indices": [65, 77]}, {"text": "travel", "indices": [78, 85]}, {"text": "traveler", "indices": [86, 95]}], "sentiment_text": "she knows it is not something to run from now. do not run, do not.", "parse": [{"she": {"pos_tag": "PRP", "lemma": "she", "ner": "O"}, "knows": {"pos_tag": "VBZ", "lemma": "know", "ner": "O", "nsubj": "she", "ccomp": "something", "punct": "."}, "it": {"pos_tag": "PRP", "lemma": "it", "ner": "O"}, "is": {"pos_tag": "VBZ", "lemma": "be", "ner": "O"}, "not": {"pos_tag": "RB", "lemma": "not", "ner": "O"}, "something": {"pos_tag": "NN", "lemma": "something", "ner": "O", "nsubj": "it", "cop": "is", "neg": "not", "acl": "run"}, "to": {"pos_tag": "TO", "lemma": "to", "ner": "O"}, "run": {"pos_tag": "VB", "lemma": "run", "ner": "O", "mark": "to", "nmod": "now"}, "from": {"pos_tag": "IN", "lemma": "from", "ner": "O"}, "now": {"pos_tag": "RB", "lemma": "now", "ner": "O", "case": "from"}, ".": {"pos_tag": ".", "lemma": ".", "ner": "O"}}, {"do": {"pos_tag": "VBP", "lemma": "do", "ner": "O", "ccomp": "run", "punct": ".", "neg": "not"}, "not": {"pos_tag": "RB", "lemma": "not", "ner": "O"}, "run": {"pos_tag": "VB", "lemma": "run", "ner": "O", "aux": "do", "neg": "not"}, ",": {"pos_tag": ",", "lemma": ",", "ner": "O"}, ".": {"pos_tag": ".", "lemma": ".", "ner": "O"}}], "emoticons": [], "opinionate": [true, true]}], "2305646365": [{"id": 766364377209450496, "datetime": "Thu Aug 18 20:01:20 +0000 2016", "text": "went on a little adventure with some awesome people the other day @ Niagara Gorge https://t.co/K1zN0fVASG", "user_id": 2305646365, "user_location_str": "Toronto", "location": {"type": "Point", "coordinates": [43.1208, -79.0705]}, "hashtags": [], "sentiment_text": "went on a little adventure with some awesome people the other day @ niagara gorge", "parse": [{"went": {"pos_tag": "VBD", "lemma": "go", "ner": "O", "nmod": "people", "nsubj": "gorge"}, "on": {"pos_tag": "IN", "lemma": "on", "ner": "O"}, "a": {"pos_tag": "DT", "lemma": "a", "ner": "O"}, "little": {"pos_tag": "JJ", "lemma": "little", "ner": "O"}, "adventure": {"pos_tag": "NN", "lemma": "adventure", "ner": "O", "case": "on", "det": "a", "amod": "little"}, "with": {"pos_tag": "IN", "lemma": "with", "ner": "O"}, "some": {"pos_tag": "DT", "lemma": "some", "ner": "O"}, "awesome": {"pos_tag": "JJ", "lemma": "awesome", "ner": "O"}, "people": {"pos_tag": "NNS", "lemma": "people", "ner": "O", "case": "with", "det": "some", "amod": "awesome", "dep": "day"}, "the": {"pos_tag": "DT", "lemma": "the", "ner": "O"}, "other": {"pos_tag": "JJ", "lemma": "other", "ner": "O"}, "day": {"pos_tag": "NN", "lemma": "day", "ner": "TIME", "det": "the", "amod": "other", "dep": "@"}, "@": {"pos_tag": "SYM", "lemma": "@", "ner": "O"}, "niagara": {"pos_tag": "NNP", "lemma": "niagara", "ner": "LOCATION"}, "gorge": {"pos_tag": "NNP", "lemma": "gorge", "ner": "LOCATION", "compound": "niagara"}}], "emoticons": [], "opinionate": [true]}], "138108816": [{"id": 593737629746667521, "datetime": "Thu Apr 30 11:24:16 +0000 2015", "text": "On vacation and @KLambercy is like a drill sergeant. Wake up at 06:00h. Breakfast in 15min sharp Private! Boss boss boss #whatavacation", "user_id": 138108816, "user_location_str": "Hogwarts", "location": {"type": "Point", "coordinates": [43.11582366, -79.07022687]}, "hashtags": [{"text": "whatavacation", "indices": [121, 135]}], "sentiment_text": "on vacation and is like a drill sergeant. wake up at :h. breakfast in min sharp private! boss boss", "parse": [{"on": {"pos_tag": "IN", "lemma": "on", "ner": "O"}, "vacation": {"pos_tag": "NN", "lemma": "vacation", "ner": "O", "case": "on"}, "and": {"pos_tag": "CC", "lemma": "and", "ner": "O"}, "is": {"pos_tag": "VBZ", "lemma": "be", "ner": "O"}, "like": {"pos_tag": "IN", "lemma": "like", "ner": "O"}, "a": {"pos_tag": "DT", "lemma": "a", "ner": "O"}, "drill": {"pos_tag": "NN", "lemma": "drill", "ner": "O"}, "sergeant": {"pos_tag": "NN", "lemma": "sergeant", "ner": "TITLE", "nmod": "vacation", "nsubj": "and", "cop": "is", "case": "like", "det": "a", "compound": "drill", "punct": "."}, ".": {"pos_tag": ".", "lemma": ".", "ner": "O"}}, {"wake": {"pos_tag": "VB", "lemma": "wake", "ner": "O", "compound:prt": "up", "nmod": "at", "punct": "!", "dep": "h."}, "up": {"pos_tag": "RP", "lemma": "up", "ner": "O"}, "at": {"pos_tag": "IN", "lemma": "at", "ner": "O"}, ":": {"pos_tag": ":", "lemma": ":", "ner": "O"}, "h.": {"pos_tag": "VB", "lemma": "h.", "ner": "O", "dobj": "breakfast"}, "breakfast": {"pos_tag": "NNP", "lemma": "breakfast", "ner": "O", "nmod": "min"}, "in": {"pos_tag": "IN", "lemma": "in", "ner": "O"}, "min": {"pos_tag": "NN", "lemma": "min", "ner": "O", "case": "in", "amod": "private"}, "sharp": {"pos_tag": "JJ", "lemma": "sharp", "ner": "O"}, "private": {"pos_tag": "JJ", "lemma": "private", "ner": "TITLE", "amod": "sharp"}, "!": {"pos_tag": ".", "lemma": "!", "ner": "O"}}, {"boss": {"pos_tag": "NN", "lemma": "boss", "ner": "TITLE"}}], "emoticons": [], "opinionate": [true, true, false]}], "1618815852": [{"id": 987096836220469248, "datetime": "Thu Apr 19 22:33:19 +0000 2018", "text": "Omg this is amazing!!!! #deer #theviewsgotbetter #soamazing #nature #animals #love @ Great Wolf... https://t.co/UQCCMofp2u", "user_id": 1618815852, "user_location_str": "Toronto, Ontario", "location": {"type": "Point", "coordinates": [43.11611133, -79.07118608]}, "hashtags": [{"text": "deer", "indices": [24, 29]}, {"text": "theviewsgotbetter", "indices": [30, 48]}, {"text": "soamazing", "indices": [49, 59]}, {"text": "nature", "indices": [60, 67]}, {"text": "animals", "indices": [68, 76]}, {"text": "love", "indices": [77, 82]}], "sentiment_text": "omg this amazing! @ great wolf.", "parse": [{"omg": {"pos_tag": "NN", "lemma": "omg", "ner": "O", "dep": "amazing", "punct": "!"}, "this": {"pos_tag": "DT", "lemma": "this", "ner": "O"}, "amazing": {"pos_tag": "JJ", "lemma": "amazing", "ner": "O", "det": "this"}, "!": {"pos_tag": ".", "lemma": "!", "ner": "O"}}, {"@": {"pos_tag": "SYM", "lemma": "@", "ner": "O"}, "great": {"pos_tag": "NNP", "lemma": "great", "ner": "PERSON", "dep": "wolf"}, "wolf": {"pos_tag": "NNP", "lemma": "wolf", "ner": "PERSON", "punct": "."}, ".": {"pos_tag": ".", "lemma": ".", "ner": "O"}}], "emoticons": [], "opinionate": [true, false]}, {"id": 987035309807353857, "datetime": "Thu Apr 19 18:28:50 +0000 2018", "text": "And we arrived safe and sound! Checkout our suite!! [?] #gwl2018 #suite #hotel #travel... https://t.co/xbZVJK1FTq", "user_id": 1618815852, "user_location_str": "Toronto, Ontario", "location": {"type": "Point", "coordinates": [43.11650697, -79.07199969]}, "hashtags": [{"text": "gwl2018", "indices": [57, 65]}, {"text": "suite", "indices": [66, 72]}, {"text": "hotel", "indices": [73, 79]}, {"text": "travel", "indices": [80, 87]}], "sentiment_text": "and we arrived safe and sound! checkout our suite! [?] .", "parse": [{"and": {"pos_tag": "CC", "lemma": "and", "ner": "O"}, "we": {"pos_tag": "PRP", "lemma": "we", "ner": "O"}, "arrived": {"pos_tag": "VBD", "lemma": "arrive", "ner": "O", "cc": "and", "nsubj": "we", "xcomp": "safe", "punct": "!"}, "safe": {"pos_tag": "JJ", "lemma": "safe", "ner": "O", "cc": "and", "conj": "sound"}, "sound": {"pos_tag": "JJ", "lemma": "sound", "ner": "O"}, "!": {"pos_tag": ".", "lemma": "!", "ner": "O"}}, {"checkout": {"pos_tag": "NNP", "lemma": "checkout", "ner": "O", "dep": "suite", "punct": "!"}, "our": {"pos_tag": "PRP$", "lemma": "we", "ner": "O"}, "suite": {"pos_tag": "NN", "lemma": "suite", "ner": "O", "nmod:poss": "our"}, "!": {"pos_tag": ".", "lemma": "!", "ner": "O"}}, {"-lsb-": {"pos_tag": "-LRB-", "lemma": "-lsb-", "ner": "O", "punct": "-rsb-"}, "?": {"pos_tag": ".", "lemma": "?", "ner": "O"}, "-rsb-": {"pos_tag": "-RRB-", "lemma": "-rsb-", "ner": "O"}}, {".": {"pos_tag": ".", "lemma": ".", "ner": "O"}}], "emoticons": [], "opinionate": [true, true, false, false]}], "68947174": [{"id": 849779847866048512, "datetime": "Thu Apr 06 00:24:38 +0000 2017", "text": "Nature is my favorite place to be [?] @ Niagara Whirlpool https://t.co/oKa6KAygAu", "user_id": 68947174, "user_location_str": "", "location": {"type": "Point", "coordinates": [43.1208, -79.0699]}, "hashtags": [], "sentiment_text": "nature is my favorite place to be [?] @ niagara whirlpool", "parse": [{"nature": {"pos_tag": "NNP", "lemma": "nature", "ner": "O"}, "is": {"pos_tag": "VBZ", "lemma": "be", "ner": "O"}, "my": {"pos_tag": "PRP$", "lemma": "my", "ner": "O"}, "favorite": {"pos_tag": "JJ", "lemma": "favorite", "ner": "O"}, "place": {"pos_tag": "NN", "lemma": "place", "ner": "O", "nsubj": "nature", "cop": "is", "nmod:poss": "my", "amod": "favorite", "acl": "-lsb-", "punct": "-rsb-"}, "to": {"pos_tag": "TO", "lemma": "to", "ner": "O"}, "be": {"pos_tag": "VB", "lemma": "be", "ner": "O"}, "-lsb-": {"pos_tag": "-LRB-", "lemma": "-lsb-", "ner": "O", "mark": "to", "aux": "be"}, "?": {"pos_tag": ".", "lemma": "?", "ner": "O"}, "-rsb-": {"pos_tag": "-RRB-", "lemma": "-rsb-", "ner": "O"}}, {"@": {"pos_tag": "SYM", "lemma": "@", "ner": "O"}, "niagara": {"pos_tag": "NNP", "lemma": "niagara", "ner": "O"}, "whirlpool": {"pos_tag": "NNP", "lemma": "whirlpool", "ner": "O", "dep": "@", "compound": "niagara"}}], "emoticons": [], "opinionate": [true, false]}], "61538004": [{"id": 1033454814255083527, "datetime": "Sat Aug 25 20:43:23 +0000 2018", "text": "Had an amazing time hiking down by the Niagara River with niagara_outfitters this morning!...#nature... https://t.co/koJteW7JEH", "user_id": 61538004, "user_location_str": "New York, New York", "location": {"type": "Point", "coordinates": [43.1208, -79.0705]}, "hashtags": [{"text": "nature", "indices": [97, 104]}], "sentiment_text": "had an amazing time hiking down by the niagara river with niagara_outfitters this morning!.", "parse": [{"had": {"pos_tag": "VBD", "lemma": "have", "ner": "O", "dobj": "time", "punct": "!"}, "an": {"pos_tag": "DT", "lemma": "a", "ner": "O"}, "amazing": {"pos_tag": "JJ", "lemma": "amazing", "ner": "O"}, "time": {"pos_tag": "NN", "lemma": "time", "ner": "O", "det": "an", "amod": "amazing", "dep": "hiking"}, "hiking": {"pos_tag": "VBG", "lemma": "hike", "ner": "O", "compound:prt": "down", "nmod": "outfitters", "nmod:tmod": "morning"}, "down": {"pos_tag": "RP", "lemma": "down", "ner": "O"}, "by": {"pos_tag": "IN", "lemma": "by", "ner": "O"}, "the": {"pos_tag": "DT", "lemma": "the", "ner": "O"}, "niagara": {"pos_tag": "NN", "lemma": "niagara", "ner": "O"}, "river": {"pos_tag": "NNP", "lemma": "river", "ner": "TITLE", "case": "by", "det": "the", "compound": "niagara"}, "with": {"pos_tag": "IN", "lemma": "with", "ner": "O"}, "_": {"pos_tag": "CD", "lemma": "_", "ner": "NUMBER"}, "outfitters": {"pos_tag": "NNS", "lemma": "outfitter", "ner": "O", "case": "with", "compound": "niagara", "nummod": "_"}, "this": {"pos_tag": "DT", "lemma": "this", "ner": "TIME"}, "morning": {"pos_tag": "NN", "lemma": "morning", "ner": "TIME", "det": "this"}, "!": {"pos_tag": ".", "lemma": "!", "ner": "O"}}, {".": {"pos_tag": ".", "lemma": ".", "ner": "O"}}], "emoticons": [], "opinionate": [true, false]}], "69064286": [{"id": 835569487177003008, "datetime": "Sat Feb 25 19:17:44 +0000 2017", "text": "Checking out the views before Great Wolf Lodge!! #niagarafalls #whirlpool #nature #love @... https://t.co/Jmu5MemtE0", "user_id": 69064286, "user_location_str": "Toronto, Ontario", "location": {"type": "Point", "coordinates": [43.118, -79.0688]}, "hashtags": [{"text": "niagarafalls", "indices": [49, 62]}, {"text": "whirlpool", "indices": [63, 73]}, {"text": "nature", "indices": [74, 81]}, {"text": "love", "indices": [82, 87]}], "sentiment_text": "checking out the views before great wolf lodge! @.", "parse": [{"checking": {"pos_tag": "VBG", "lemma": "check", "ner": "O", "compound:prt": "out", "dobj": "views", "nmod": "lodge", "punct": "!"}, "out": {"pos_tag": "RP", "lemma": "out", "ner": "O"}, "the": {"pos_tag": "DT", "lemma": "the", "ner": "O"}, "views": {"pos_tag": "NNS", "lemma": "view", "ner": "O", "det": "the"}, "before": {"pos_tag": "IN", "lemma": "before", "ner": "O"}, "great": {"pos_tag": "JJ", "lemma": "great", "ner": "O"}, "wolf": {"pos_tag": "NNP", "lemma": "wolf", "ner": "O"}, "lodge": {"pos_tag": "NNP", "lemma": "lodge", "ner": "O", "case": "before", "amod": "great", "compound": "wolf"}, "!": {"pos_tag": ".", "lemma": "!", "ner": "O"}}, {"@": {"pos_tag": "SYM", "lemma": "@", "ner": "O", "punct": "."}, ".": {"pos_tag": ".", "lemma": ".", "ner": "O"}}], "emoticons": [], "opinionate": [true, false]}], "3233106586": [{"id": 707356581092982784, "datetime": "Wed Mar 09 00:05:25 +0000 2016", "text": "Cold Wash #vsco #VSCOfilm #niagarafalls #nature @ Niagara Whirlpool https://t.co/26y3y1EO0d", "user_id": 3233106586, "user_location_str": "London, England", "location": {"type": "Point", "coordinates": [43.120783, -79.069891]}, "hashtags": [{"text": "vsco", "indices": [12, 17]}, {"text": "VSCOfilm", "indices": [18, 27]}, {"text": "niagarafalls", "indices": [28, 41]}, {"text": "nature", "indices": [42, 49]}], "sentiment_text": "cold wash @ niagara whirlpool", "parse": [{"cold": {"pos_tag": "NNP", "lemma": "cold", "ner": "O", "dep": "wash"}, "wash": {"pos_tag": "NNP", "lemma": "wash", "ner": "STATE_OR_PROVINCE", "acl:relcl": "whirlpool"}, "@": {"pos_tag": "SYM", "lemma": "@", "ner": "O"}, "niagara": {"pos_tag": "NNP", "lemma": "niagara", "ner": "LOCATION"}, "whirlpool": {"pos_tag": "NNP", "lemma": "whirlpool", "ner": "LOCATION", "dep": "@", "compound": "niagara"}}], "emoticons": [], "opinionate": [true]}], "22331604": [{"id": 894374112264679424, "datetime": "Mon Aug 07 01:46:19 +0000 2017", "text": "Just hugging trees!  #vegan #hottie #travel #traveler #travelblog #travelblogger... https://t.co/CAsQUiE5eC", "user_id": 22331604, "user_location_str": "", "location": {"type": "Point", "coordinates": [43.1208, -79.0705]}, "hashtags": [{"text": "vegan", "indices": [24, 30]}, {"text": "hottie", "indices": [31, 38]}, {"text": "travel", "indices": [39, 46]}, {"text": "traveler", "indices": [47, 56]}, {"text": "travelblog", "indices": [57, 68]}, {"text": "travelblogger", "indices": [69, 83]}], "sentiment_text": "just hugging trees! .", "parse": [{"just": {"pos_tag": "RB", "lemma": "just", "ner": "O"}, "hugging": {"pos_tag": "VBG", "lemma": "hug", "ner": "O", "advmod": "just", "dobj": "trees", "punct": "!"}, "trees": {"pos_tag": "NNS", "lemma": "tree", "ner": "O"}, "!": {"pos_tag": ".", "lemma": "!", "ner": "O"}}, {".": {"pos_tag": ".", "lemma": ".", "ner": "O"}}], "emoticons": [], "opinionate": [true, false]}], "1319104112": [{"id": 653652198975500288, "datetime": "Mon Oct 12 19:23:23 +0000 2015", "text": "always a beautiful day for an adventure @ Niagara Gorge https://t.co/pMkjCRp1ut", "user_id": 1319104112, "user_location_str": "", "location": {"type": "Point", "coordinates": [43.1208, -79.0705]}, "hashtags": [], "sentiment_text": "always a beautiful day for an adventure @ niagara gorge", "parse": [{"always": {"pos_tag": "RB", "lemma": "always", "ner": "O"}, "a": {"pos_tag": "DT", "lemma": "a", "ner": "O"}, "beautiful": {"pos_tag": "JJ", "lemma": "beautiful", "ner": "O"}, "day": {"pos_tag": "NN", "lemma": "day", "ner": "TIME", "advmod": "always", "det": "a", "amod": "beautiful", "nmod": "adventure", "dep": "gorge"}, "for": {"pos_tag": "IN", "lemma": "for", "ner": "O"}, "an": {"pos_tag": "DT", "lemma": "a", "ner": "O"}, "adventure": {"pos_tag": "NN", "lemma": "adventure", "ner": "O", "case": "for", "det": "an", "dep": "@"}, "@": {"pos_tag": "SYM", "lemma": "@", "ner": "O"}, "niagara": {"pos_tag": "NNP", "lemma": "niagara", "ner": "O"}, "gorge": {"pos_tag": "NNP", "lemma": "gorge", "ner": "O", "compound": "niagara"}}], "emoticons": [], "opinionate": [true]}], "26052862": [{"id": 637004001842737152, "datetime": "Thu Aug 27 20:49:23 +0000 2015", "text": "Niagara Gorge -ous ! View from the Whirlpool Aero Car in @niagaraparks ontariotravel #canada #travel... https://t.co/eM9vAzQ6gM", "user_id": 26052862, "user_location_str": "Toronto", "location": {"type": "Point", "coordinates": [43.11798, -79.06877]}, "hashtags": [{"text": "canada", "indices": [85, 92]}, {"text": "travel", "indices": [93, 100]}], "sentiment_text": "niagara gorge -ous ! view from the whirlpool aero car in ontariotravel .", "parse": [{"niagara": {"pos_tag": "NNP", "lemma": "niagara", "ner": "O"}, "gorge": {"pos_tag": "NNP", "lemma": "gorge", "ner": "O", "compound": "niagara", "punct": "!", "dep": "ous"}, "-": {"pos_tag": ":", "lemma": "-", "ner": "O"}, "ous": {"pos_tag": "NN", "lemma": "ous", "ner": "O"}, "!": {"pos_tag": ".", "lemma": "!", "ner": "O"}}, {"view": {"pos_tag": "NNP", "lemma": "view", "ner": "O", "nmod": "ontariotravel", "punct": "."}, "from": {"pos_tag": "IN", "lemma": "from", "ner": "O"}, "the": {"pos_tag": "DT", "lemma": "the", "ner": "O"}, "whirlpool": {"pos_tag": "NNP", "lemma": "whirlpool", "ner": "ORGANIZATION"}, "aero": {"pos_tag": "NNP", "lemma": "aero", "ner": "ORGANIZATION"}, "car": {"pos_tag": "NN", "lemma": "car", "ner": "O", "case": "from", "det": "the", "compound": "aero"}, "in": {"pos_tag": "IN", "lemma": "in", "ner": "O"}, "ontariotravel": {"pos_tag": "NN", "lemma": "ontariotravel", "ner": "O", "case": "in"}, ".": {"pos_tag": ".", "lemma": ".", "ner": "O"}}], "emoticons": [], "opinionate": [false, true]}], "31575957": [{"id": 884100285739581440, "datetime": "Sun Jul 09 17:21:48 +0000 2017", "text": "Something about nature that is truly calming. @ Niagara Whirlpool https://t.co/t9oeb8bk9j", "user_id": 31575957, "user_location_str": "Philadelphia, PA", "location": {"type": "Point", "coordinates": [43.1208, -79.0699]}, "hashtags": [], "sentiment_text": "something about nature that is truly calming. @ niagara whirlpool", "parse": [{"something": {"pos_tag": "NN", "lemma": "something", "ner": "O", "nmod": "nature", "punct": "."}, "about": {"pos_tag": "IN", "lemma": "about", "ner": "O"}, "nature": {"pos_tag": "NN", "lemma": "nature", "ner": "O", "case": "about", "acl:relcl": "calming"}, "that": {"pos_tag": "WDT", "lemma": "that", "ner": "O"}, "is": {"pos_tag": "VBZ", "lemma": "be", "ner": "O"}, "truly": {"pos_tag": "RB", "lemma": "truly", "ner": "O"}, "calming": {"pos_tag": "JJ", "lemma": "calming", "ner": "O", "nsubj": "that", "cop": "is", "advmod": "truly"}, ".": {"pos_tag": ".", "lemma": ".", "ner": "O"}}, {"@": {"pos_tag": "SYM", "lemma": "@", "ner": "O"}, "niagara": {"pos_tag": "NNP", "lemma": "niagara", "ner": "O"}, "whirlpool": {"pos_tag": "NNP", "lemma": "whirlpool", "ner": "O", "dep": "@", "compound": "niagara"}}], "emoticons": [], "opinionate": [true, false]}], "824453620892663808": [{"id": 897556221498081280, "datetime": "Tue Aug 15 20:30:53 +0000 2017", "text": "a brand new #adventure #niagrafalls @ Whirlpool Aero Car https://t.co/CHbLrZr3J6", "user_id": 824453620892663808, "user_location_str": "United States", "location": {"type": "Point", "coordinates": [43.118, -79.0688]}, "hashtags": [{"text": "adventure", "indices": [12, 22]}, {"text": "niagrafalls", "indices": [23, 35]}], "sentiment_text": "a brand new @ whirlpool aero car", "parse": [{"a": {"pos_tag": "DT", "lemma": "a", "ner": "O"}, "brand": {"pos_tag": "NN", "lemma": "brand", "ner": "O", "det": "a", "dep": "new"}, "new": {"pos_tag": "JJ", "lemma": "new", "ner": "O", "acl:relcl": "car"}, "@": {"pos_tag": "SYM", "lemma": "@", "ner": "O"}, "whirlpool": {"pos_tag": "NNP", "lemma": "whirlpool", "ner": "ORGANIZATION"}, "aero": {"pos_tag": "NNP", "lemma": "aero", "ner": "ORGANIZATION"}, "car": {"pos_tag": "NNP", "lemma": "car", "ner": "O", "dep": "@", "compound": "aero"}}], "emoticons": [], "opinionate": [true]}], "887721782": [{"id": 959428232654159872, "datetime": "Fri Feb 02 14:08:10 +0000 2018", "text": "Jade and Kaydyn doing morning yoga! #yoga #greatWolfLodge #greatTime #vacation #familyTime... https://t.co/RGgI57hn1P", "user_id": 887721782, "user_location_str": "Peterborough Ontario", "location": {"type": "Point", "coordinates": [43.11650697, -79.07199969]}, "hashtags": [{"text": "yoga", "indices": [36, 41]}, {"text": "greatWolfLodge", "indices": [42, 57]}, {"text": "greatTime", "indices": [58, 68]}, {"text": "vacation", "indices": [69, 78]}, {"text": "familyTime", "indices": [79, 90]}], "sentiment_text": "jade and kaydyn doing morning yoga! .", "parse": [{"jade": {"pos_tag": "NNP", "lemma": "jade", "ner": "PERSON", "cc": "and", "conj": "kaydyn", "acl": "doing", "punct": "!"}, "and": {"pos_tag": "CC", "lemma": "and", "ner": "O"}, "kaydyn": {"pos_tag": "NNP", "lemma": "kaydyn", "ner": "PERSON"}, "doing": {"pos_tag": "VBG", "lemma": "do", "ner": "O", "dobj": "yoga"}, "morning": {"pos_tag": "NN", "lemma": "morning", "ner": "TIME"}, "yoga": {"pos_tag": "NN", "lemma": "yoga", "ner": "RELIGION", "compound": "morning"}, "!": {"pos_tag": ".", "lemma": "!", "ner": "O"}}, {".": {"pos_tag": ".", "lemma": ".", "ner": "O"}}], "emoticons": [], "opinionate": [true, false]}], "76394861": [{"id": 574072381297266688, "datetime": "Sat Mar 07 05:01:36 +0000 2015", "text": "Fire alarm finally stops after what seems like forever but was probably 20 minutes. Always an adventure @GreatWolfLodge", "user_id": 76394861, "user_location_str": "Toronto, Canada", "location": {"type": "Point", "coordinates": [43.11553208, -79.07062712]}, "hashtags": [], "sentiment_text": "fire alarm finally stops after what seems like forever but was probably minutes. always an adventure", "parse": [{"fire": {"pos_tag": "NN", "lemma": "fire", "ner": "CAUSE_OF_DEATH"}, "alarm": {"pos_tag": "NN", "lemma": "alarm", "ner": "O", "compound": "fire"}, "finally": {"pos_tag": "RB", "lemma": "finally", "ner": "O"}, "stops": {"pos_tag": "VBZ", "lemma": "stop", "ner": "O", "nsubj": "alarm", "advmod": "finally", "advcl": "seems", "punct": "."}, "after": {"pos_tag": "IN", "lemma": "after", "ner": "O"}, "what": {"pos_tag": "WP", "lemma": "what", "ner": "O"}, "seems": {"pos_tag": "VBZ", "lemma": "seem", "ner": "O", "mark": "after", "nsubj": "what", "advcl": "forever", "cc": "but", "conj": "was"}, "like": {"pos_tag": "IN", "lemma": "like", "ner": "O"}, "forever": {"pos_tag": "RB", "lemma": "forever", "ner": "O", "case": "like"}, "but": {"pos_tag": "CC", "lemma": "but", "ner": "O"}, "was": {"pos_tag": "VBD", "lemma": "be", "ner": "O", "advmod": "probably"}, "probably": {"pos_tag": "RB", "lemma": "probably", "ner": "O", "nmod:npmod": "minutes"}, "minutes": {"pos_tag": "NNS", "lemma": "minute", "ner": "O"}, ".": {"pos_tag": ".", "lemma": ".", "ner": "O"}}, {"always": {"pos_tag": "RB", "lemma": "always", "ner": "O"}, "an": {"pos_tag": "DT", "lemma": "a", "ner": "O"}, "adventure": {"pos_tag": "NN", "lemma": "adventure", "ner": "O", "dep": "always", "det": "an"}}], "emoticons": [], "opinionate": [true, true]}]}