{"3599637021": [{"id": 824117237606969344, "datetime": "Wed Jan 25 04:50:35 +0000 2017", "text": "Outdoors. #photography #photojournalism #photoshoot #photographer #nature #naturephotography @... https://t.co/N15sNZQVwc", "user_id": 3599637021, "user_location_str": "Toronto, Ontario", "location": {"type": "Point", "coordinates": [43.07658669, -79.09454826]}, "hashtags": [{"text": "photography", "indices": [10, 22]}, {"text": "photojournalism", "indices": [23, 39]}, {"text": "photoshoot", "indices": [40, 51]}, {"text": "photographer", "indices": [52, 65]}, {"text": "nature", "indices": [66, 73]}, {"text": "naturephotography", "indices": [74, 92]}], "sentiment_text": "outdoors. @.", "parse": [{"outdoors": {"pos_tag": "RB", "lemma": "outdoors", "ner": "O", "punct": "."}, ".": {"pos_tag": ".", "lemma": ".", "ner": "O"}}, {"@": {"pos_tag": "SYM", "lemma": "@", "ner": "O", "punct": "."}, ".": {"pos_tag": ".", "lemma": ".", "ner": "O"}}], "emoticons": [], "opinionate": [false, false]}], "93977567": [{"id": 838206029385064448, "datetime": "Sun Mar 05 01:54:25 +0000 2017", "text": "Incredible view from inside\\behind the falls. #BoogieDoesNiagraFalls #travel #ElsaWasHere... https://t.co/9tfrKwUaMW", "user_id": 93977567, "user_location_str": "Noth Bend, WA", "location": {"type": "Point", "coordinates": [43.07658669, -79.09454826]}, "hashtags": [{"text": "BoogieDoesNiagraFalls", "indices": [46, 68]}, {"text": "travel", "indices": [69, 76]}, {"text": "ElsaWasHere", "indices": [77, 89]}], "sentiment_text": "incredible view from inside\\behind the falls. .", "parse": [{"incredible": {"pos_tag": "JJ", "lemma": "incredible", "ner": "O"}, "view": {"pos_tag": "NN", "lemma": "view", "ner": "O", "amod": "incredible", "nmod": "\\"}, "from": {"pos_tag": "IN", "lemma": "from", "ner": "O"}, "inside": {"pos_tag": "JJ", "lemma": "inside", "ner": "O"}, "\\": {"pos_tag": "NN", "lemma": "\\", "ner": "O", "case": "from", "amod": "inside"}, "behind": {"pos_tag": "IN", "lemma": "behind", "ner": "O"}, "the": {"pos_tag": "DT", "lemma": "the", "ner": "O", "case": "behind"}, "falls": {"pos_tag": "VBZ", "lemma": "fall", "ner": "O", "nsubj": "view", "advmod": "the", "punct": "."}, ".": {"pos_tag": ".", "lemma": ".", "ner": "O"}}, {".": {"pos_tag": ".", "lemma": ".", "ner": "O"}}], "emoticons": [], "opinionate": [true, false]}], "11553042": [{"id": 820825463559962624, "datetime": "Mon Jan 16 02:50:15 +0000 2017", "text": "What an amazing view ! Winter, my favorite season :) #travel #sundayfunday #canadianfalls... https://t.co/qDQUEiGCHU", "user_id": 11553042, "user_location_str": "\u00dcT: 20.703259,-103.358564", "location": {"type": "Point", "coordinates": [43.07658669, -79.09454826]}, "hashtags": [{"text": "travel", "indices": [53, 60]}, {"text": "sundayfunday", "indices": [61, 74]}, {"text": "canadianfalls", "indices": [75, 89]}], "sentiment_text": "what an amazing view ! winter, my favorite season :) .", "parse": [{"what": {"pos_tag": "WDT", "lemma": "what", "ner": "O", "dep": "an"}, "an": {"pos_tag": "DT", "lemma": "a", "ner": "O"}, "amazing": {"pos_tag": "JJ", "lemma": "amazing", "ner": "O"}, "view": {"pos_tag": "NN", "lemma": "view", "ner": "O", "dep": "what", "amod": "amazing", "punct": "!"}, "!": {"pos_tag": ".", "lemma": "!", "ner": "O"}}, {"winter": {"pos_tag": "NNP", "lemma": "winter", "ner": "O", "punct": ".", "appos": ":-rrb-"}, ",": {"pos_tag": ",", "lemma": ",", "ner": "O"}, "my": {"pos_tag": "PRP$", "lemma": "my", "ner": "O"}, "favorite": {"pos_tag": "JJ", "lemma": "favorite", "ner": "O"}, "season": {"pos_tag": "NN", "lemma": "season", "ner": "O"}, ":-rrb-": {"pos_tag": "NN", "lemma": ":-rrb-", "ner": "O", "nmod:poss": "my", "amod": "favorite", "compound": "season"}, ".": {"pos_tag": ".", "lemma": ".", "ner": "O"}}], "emoticons": [], "opinionate": [true, true]}]}