{"324832283": [{"id": 992842802546577408, "datetime": "Sat May 05 19:05:44 +0000 2018", "text": "Hiking with @ingasokol #Spring #Canada #nature [?] (@ Swayze Falls) https://t.co/3XRTdKInLG https://t.co/wES7y53Fel", "user_id": 324832283, "user_location_str": "Montreal boy in Ontario,Canada", "location": {"type": "Point", "coordinates": [43.09270009, -79.30228521]}, "hashtags": [{"text": "Spring", "indices": [23, 30]}, {"text": "Canada", "indices": [31, 38]}, {"text": "nature", "indices": [39, 46]}], "sentiment_text": "hiking with [?] (@ swayze falls)", "parse": [{"hiking": {"pos_tag": "VBG", "lemma": "hike", "ner": "O", "nmod": "-lsb-", "punct": "-rsb-"}, "with": {"pos_tag": "IN", "lemma": "with", "ner": "O"}, "-lsb-": {"pos_tag": "-LRB-", "lemma": "-lsb-", "ner": "O", "case": "with"}, "?": {"pos_tag": ".", "lemma": "?", "ner": "O"}, "-rsb-": {"pos_tag": "-RRB-", "lemma": "-rsb-", "ner": "O"}}, {"-lrb-": {"pos_tag": "-LRB-", "lemma": "-lrb-", "ner": "O"}, "@": {"pos_tag": "SYM", "lemma": "@", "ner": "O"}, "swayze": {"pos_tag": "NNP", "lemma": "swayze", "ner": "LOCATION"}, "falls": {"pos_tag": "NNP", "lemma": "falls", "ner": "CAUSE_OF_DEATH", "punct": "-rrb-", "dep": "@", "compound": "swayze"}, "-rrb-": {"pos_tag": "-RRB-", "lemma": "-rrb-", "ner": "O"}}], "emoticons": [], "opinionate": [true, true]}]}